FoodApp_Lib/__init__.py
FoodApp_Lib/admin.py
FoodApp_Lib/forms.py
FoodApp_Lib/models.py
FoodApp_Lib/utils.py
FoodApp_Lib/views.py
FoodApp_lib-0.1.0.dist-info/LICENCE
FoodApp_lib-0.1.0.dist-info/METADATA
FoodApp_lib-0.1.0.dist-info/WHEEL
FoodApp_lib-0.1.0.dist-info/top_level.txt
FoodApp_lib-0.1.0.dist-info/RECORD
