Metadata-Version: 2.1
Name: FoodApp_lib
Version: 0.1.0
Summary: A library for managing food orders and employees in a Django application.
Author: Aakash
Author-email: aakashbabu75399@gmail.com
Classifier: Programming Language :: Python :: 3
Classifier: Programming Language :: Python :: 3.12
Classifier: License :: OSI Approved :: MIT License
License-File: LICENCE
Requires-Dist: django>=3.0
Requires-Dist: boto3
